pypsicquic/__init__.py
pypsicquic-0.2.0.dist-info/METADATA
pypsicquic-0.2.0.dist-info/WHEEL
pypsicquic-0.2.0.dist-info/RECORD
