Metadata-Version: 2.1
Name: pypsicquic
Version: 0.2.0
Summary: 
Author: glaunay
Author-email: pitooon@gmail.com
Requires-Python: >=3.9,<4.0
Classifier: Programming Language :: Python :: 3
Classifier: Programming Language :: Python :: 3.9
Classifier: Programming Language :: Python :: 3.10
Classifier: Programming Language :: Python :: 3.11
Classifier: Programming Language :: Python :: 3.12
Requires-Dist: networkx (>=2.8.7,<3.0.0)
Requires-Dist: requests (>=2.28.1,<3.0.0)
Requires-Dist: scipy (>=1.9.3,<2.0.0)
